tests/__init__.py
tests/helpers/__init__.py
tests/helpers/bunch.py
tests/test_init_transcription_service/__init__.py
tests/test_init_transcription_service/helpers.py
tests/test_init_transcription_service/test_it_creates_a_service_instance_for_module_path.py
tests/test_init_transcription_service/test_it_raises_exception_for_missing_required_config.py
tests/test_init_transcription_service/test_it_reads_config_from_env.py
tests/test_transcribe/__init__.py
tests/test_transcribe/helpers.py
tests/test_transcribe/test_it_accepts_a_completed_result_with_empty_transcript.py
tests/test_transcribe/test_it_continues_to_completion_when_some_jobs_fail.py
tests/test_transcribe/test_it_handles_subtitle_generation.py
tests/test_transcribe/test_it_retries_start_transcription_job_when_limit_exceeded.py
tests/test_transcribe/test_it_uploads_multiple_jobs_and_tracks_progress_until_completion.py
tests/test_transcribe/test_it_uploads_one_jobs_and_tracks_progress_until_completion.py
transcribe_aws/__init__.py
transcribe_aws/py.typed
py_transcribe_aws-1.5.0.dist-info/LICENSE
py_transcribe_aws-1.5.0.dist-info/LICENSE_HEADER
py_transcribe_aws-1.5.0.dist-info/METADATA
py_transcribe_aws-1.5.0.dist-info/WHEEL
py_transcribe_aws-1.5.0.dist-info/top_level.txt
py_transcribe_aws-1.5.0.dist-info/RECORD
