Metadata-Version: 2.1
Name: py-transcribe-aws
Version: 1.5.0
Summary: framework for synchronous batch speech-to-text transcription using backends like AWS, Watson, etc.
Home-page: UNKNOWN
Author-email: larrykirschner@gmail.com
License: UNKNOWN
Platform: UNKNOWN
License-File: LICENSE
License-File: LICENSE_HEADER
Requires-Dist: awscli (>=1.18.165)
Requires-Dist: boto3 (>=1.16.5)
Requires-Dist: boto3-type-annotations (>=0.3.1)
Requires-Dist: requests (>=2.24.0)
Requires-Dist: py-transcribe (>=1.0.0)
